bookpicker/__init__.py
bookpicker/__main__.py
bookpicker/bookpicker.py
bookpicker-0.1.2.dist-info/licenses/LICENSE
bookpicker-0.1.2.dist-info/METADATA
bookpicker-0.1.2.dist-info/WHEEL
bookpicker-0.1.2.dist-info/entry_points.txt
bookpicker-0.1.2.dist-info/top_level.txt
bookpicker-0.1.2.dist-info/RECORD
