Metadata-Version: 2.4
Name: bookpicker
Version: 0.1.2
Summary: my cool cli app
Requires-Python: >=3.8
License-File: LICENSE
Dynamic: license-file
